supershape/__init__.py
supershape/__main__.py
supershape/blender.py
supershape/supershape.py
supershape-1.1.1.dist-info/LICENSE
supershape-1.1.1.dist-info/METADATA
supershape-1.1.1.dist-info/WHEEL
supershape-1.1.1.dist-info/top_level.txt
supershape-1.1.1.dist-info/RECORD
