Metadata-Version: 2.1
Name: supershape
Version: 1.1.1
Summary: Python code to efficiently generate 3D supershapes with optional Blender support.
Home-page: https://github.com/cheind/supershape
Author: Christoph Heindl
License: UNKNOWN
Platform: UNKNOWN
Requires-Dist: numpy
